{"jo_user1":{"jo_user_name":"duc","jo_money":0,"jo_space":75,"jo_warehouse":{"grass":14,"egg":20,"meat":10,"milk":20,"medicine_normal":8,"medicine_special":2,"food_normal":7,"food_special":5,"dog":3,"cat":1,"chicken":1,"cow":4,"ostric":1,"pig":3},"jo_grass":{"total_number":"5","step1":"1","step2":"2","step3":"2"},"jo_chicken":{"total_number":"3","list_chicken":[{"life":"80%","sickness":"90%","step":"1"},{"life":"50%","sickness":"90%","step":"3"},{"life":"30%","sickness":"90%","step":"2"}]},"jo_cow":{"total_number":"3","list_cow":[{"life":"80%","sickness":"90%","step":"1"},{"life":"50%","sickness":"90%","step":"3"},{"life":"30%","sickness":"90%","step":"2"}]},"jo_pig":{"total_number":"3","list_pig":[{"life":"80%","sickness":"90%","step":"1"},{"life":"50%","sickness":"90%","step":"3"},{"life":"30%","sickness":"90%","step":"2"}]}}}